bigsend/__init__.py
bigsend/bgclient/__main__.py
bigsend/bgclient/lib_clients.py
bigsend/bgserver/__main__.py
bigsend/bgserver/lib_server.py
bigsend-0.1.0.dist-info/METADATA
bigsend-0.1.0.dist-info/WHEEL
bigsend-0.1.0.dist-info/RECORD
